fits_sqlite/__init__.py
fits_sqlite/_packer.py
fits_sqlite/shim.py
fits_sqlite-0.1.0.dist-info/licenses/LICENSE
fits_sqlite-0.1.0.dist-info/METADATA
fits_sqlite-0.1.0.dist-info/WHEEL
fits_sqlite-0.1.0.dist-info/top_level.txt
fits_sqlite-0.1.0.dist-info/RECORD
