Metadata-Version: 2.4
Name: fits-sqlite
Version: 0.1.0
Summary: A library to embed a SQLite database within a FITS file.
Author: Juan Guerrero
License: MIT License
Project-URL: Homepage, https://github.com/coredumped/fits_sqlite
Project-URL: Bug Tracker, https://github.com/coredumped/fits_sqlite/issues
Classifier: Development Status :: 4 - Beta
Classifier: Intended Audience :: Science/Research
Classifier: License :: OSI Approved :: MIT License
Classifier: Operating System :: OS Independent
Classifier: Programming Language :: Python :: 3
Classifier: Topic :: Scientific/Engineering
Requires-Python: >=3.8
License-File: LICENSE
Requires-Dist: astropy>=5.0
Requires-Dist: numpy>=1.21
Dynamic: license-file
